TweetBirdsName/__init__.py
TweetBirdsName/bird_detection.py
TweetBirdsName/exim.py
TweetBirdsName/get_bird_names.py
TweetBirdsName/preprocess.py
IndiAves_bnt_as-0.1.dist-info/METADATA
IndiAves_bnt_as-0.1.dist-info/WHEEL
IndiAves_bnt_as-0.1.dist-info/top_level.txt
IndiAves_bnt_as-0.1.dist-info/RECORD
