Metadata-Version: 2.1
Name: IndiAves-bnt-as
Version: 0.1
Summary: Detecting bird name from short text (Tweets)
Author: Anirban Saha
Author-email: <mailme@anirbansaha.com>
Keywords: python,birding,bird name,twitter,bird name detection
Classifier: Development Status :: 1 - Planning
Classifier: Intended Audience :: Developers
Classifier: Programming Language :: Python :: 3
Classifier: Operating System :: Unix
Classifier: Operating System :: MacOS :: MacOS X
Classifier: Operating System :: Microsoft :: Windows
Requires-Dist: tweet-preprocessor
Requires-Dist: spacy
Requires-Dist: demoji
Requires-Dist: tweepy
